lab1/collatz.sv
module collatz( input logic         clk,   // Clock
		input logic 	    go,    // Load value from n; start iterating
		input logic  [31:0] n,     // Start value; only read when go = 1
		output logic [31:0] dout,  // Iteration value: true after go = 1
		output logic 	    done); // True when dout reaches 1

   always_ff @(posedge clk) begin
      if (go)		  dout <= n;
      else if (~done)
	if (dout > 1'd1)
	  if (dout[0] == 0) dout <= (dout >> 1);
	  else 		    dout <= ((3*dout)+1);
   end
   
   assign done = dout == 32'd1;
endmodule

lab1/range.sv
module range
   #(parameter
     RAM_WORDS = 16,            // Number of counts to store in RAM
     RAM_ADDR_BITS = 4)         // Number of RAM address bits
   (input logic         clk,    // Clock
    input logic 	go,     // Read start and start testing
    input logic [31:0] 	start,  // Number to start from or count to read
    output logic 	done,   // True once memory is filled
    output logic [15:0] count); // Iteration count once finished

   logic 		cgo;    // "go" for the Collatz iterator
   logic                cdone;  // "done" from the Collatz iterator
   logic [31:0] 	n;      // number to start the Collatz iterator

// verilator lint_off PINCONNECTEMPTY
   
   // Instantiate the Collatz iterator
   collatz c1(.clk(clk),
	      .go(cgo),
	      .n(n),
	      .done(cdone),
	      .dout());

   logic [RAM_ADDR_BITS - 1:0] 	 num;         // The RAM address to write
   logic 			 running = 0; // True during the iterations
   // triggers to reset we and din at the right cycles
   logic                         we_trig = 0;
   logic                         din_trig = 0;
   
   always_ff @(posedge clk) begin 
      // reset default vars
      cgo <= 0;
      done <= 0;
      we_trig <= 0;
      din_trig <= 0;
      // start of iterations
      if (go)
      begin
        running <= go;
	n <= start;
	num <= 0;
	din <= 1;
	cgo <= 1;
      end
      // iterate din
      else if (running & (~cgo) & (~cdone))   din <= (din + 1);
      // when iteration is done, trigger we
      else if (cdone)                         we_trig <= 1;
      // check to see if iterations are done
      if (we)
        begin
      if (({1'b0, num[RAM_ADDR_BITS-1:0]} == RAM_WORDS-1))
      begin
        running <= 0;
	done <= 1;
      end
      // after write, reset vars
      else  
      begin
	n <= (n+1);
	num <= (num+1);
	din_trig <= 1;
	cgo <= 1;
      end
end
      // check to reset din
      if (din_trig) din <= 1;
    end
    // assign we here so that it immediately updates with cdone
    assign we = cdone == 1 && we_trig == 0;
   
   logic                         we;
   logic [15:0] 		 din;                   // Data to write
   logic [15:0] 		 mem[RAM_WORDS - 1:0];  // The RAM itself
   logic [RAM_ADDR_BITS - 1:0] 	 addr;                  // Address to read/write

   assign addr = we ? num : start[RAM_ADDR_BITS-1:0];
   
   always_ff @(posedge clk) begin
      if (we) mem[addr] <= din;
      count <= mem[addr];      
   end
   
endmodule

lab1/range.vcd
$version Generated by VerilatedVcd $end
$date Fri Feb  9 01:49:42 2024
 $end
$timescale   1ns $end

 $scope module TOP $end
  $var wire  1 ?" clk $end
  $var wire 16 _" count [15:0] $end
  $var wire  1 W" done $end
  $var wire  1 G" go $end
  $var wire 32 O" start [31:0] $end
  $scope module range $end
   $var wire 32 o" RAM_ADDR_BITS [31:0] $end
   $var wire 32 g" RAM_WORDS [31:0] $end
   $var wire  4 C addr [3:0] $end
   $var wire  1 S cdone $end
   $var wire  1 K cgo $end
   $var wire  1 ?" clk $end
   $var wire 16 _" count [15:0] $end
   $var wire 16 k din [15:0] $end
   $var wire  1 3 din_trig $end
   $var wire  1 W" done $end
   $var wire  1 G" go $end
   $var wire 16 s mem(0) [15:0] $end
   $var wire 16 t mem(1) [15:0] $end
   $var wire 16 } mem(10) [15:0] $end
   $var wire 16 ~ mem(11) [15:0] $end
   $var wire 16 !! mem(12) [15:0] $end
   $var wire 16 "! mem(13) [15:0] $end
   $var wire 16 #! mem(14) [15:0] $end
   $var wire 16 $! mem(15) [15:0] $end
   $var wire 16 u mem(2) [15:0] $end
   $var wire 16 v mem(3) [15:0] $end
   $var wire 16 w mem(4) [15:0] $end
   $var wire 16 x mem(5) [15:0] $end
   $var wire 16 y mem(6) [15:0] $end
   $var wire 16 z mem(7) [15:0] $end
   $var wire 16 { mem(8) [15:0] $end
   $var wire 16 | mem(9) [15:0] $end
   $var wire 32 [ n [31:0] $end
   $var wire  4 c num [3:0] $end
   $var wire  1 # running $end
   $var wire 32 O" start [31:0] $end
   $var wire  1 ; we $end
   $var wire  1 + we_trig $end
   $scope module c1 $end
    $var wire  1 ?" clk $end
    $var wire  1 S done $end
    $var wire 32 7" dout [31:0] $end
    $var wire  1 K go $end
    $var wire 32 [ n [31:0] $end
   $upscope $end
  $upscope $end
 $upscope $end
$enddefinitions $end


#0
0#
0+
03
0;
b1111 C
0K
0S
b00000000000000000000000000000000 [
b0000 c
b0000000000000000 k
b0000000000000000 s
b0000000000000000 t
b0000000000000000 u
b0000000000000000 v
b0000000000000000 w
b0000000000000000 x
b0000000000000000 y
b0000000000000000 z
b0000000000000000 {
b0000000000000000 |
b0000000000000000 }
b0000000000000000 ~
b0000000000000000 !!
b0000000000000000 "!
b0000000000000000 #!
b0000000000000000 $!
b00000000000000000000000000000000 7"
0?"
1G"
b00000000000000000000001011111111 O"
0W"
b0000000000000000 _"
b00000000000000000000000000010000 g"
b00000000000000000000000000000100 o"
#10
1#
1K
b00000000000000000000001011111111 [
b0000000000000001 k
1?"
#20
0?"
#30
b00000000000000000000001011111111 7"
1?"
#40
0?"
0G"
#50
0K
1?"
#60
0?"
#70
b0000000000000010 k
b00000000000000000000100011111110 7"
1?"
#80
0?"
#90
b0000000000000011 k
b00000000000000000000010001111111 7"
1?"
#100
0?"
#110
b0000000000000100 k
b00000000000000000000110101111110 7"
1?"
#120
0?"
#130
b0000000000000101 k
b00000000000000000000011010111111 7"
1?"
#140
0?"
#150
b0000000000000110 k
b00000000000000000001010000111110 7"
1?"
#160
0?"
#170
b0000000000000111 k
b00000000000000000000101000011111 7"
1?"
#180
0?"
#190
b0000000000001000 k
b00000000000000000001111001011110 7"
1?"
#200
0?"
#210
b0000000000001001 k
b00000000000000000000111100101111 7"
1?"
#220
0?"
#230
b0000000000001010 k
b00000000000000000010110110001110 7"
1?"
#240
0?"
#250
b0000000000001011 k
b00000000000000000001011011000111 7"
1?"
#260
0?"
#270
b0000000000001100 k
b00000000000000000100010001010110 7"
1?"
#280
0?"
#290
b0000000000001101 k
b00000000000000000010001000101011 7"
1?"
#300
0?"
#310
b0000000000001110 k
b00000000000000000110011010000010 7"
1?"
#320
0?"
#330
b0000000000001111 k
b00000000000000000011001101000001 7"
1?"
#340
0?"
#350
b0000000000010000 k
b00000000000000001001100111000100 7"
1?"
#360
0?"
#370
b0000000000010001 k
b00000000000000000100110011100010 7"
1?"
#380
0?"
#390
b0000000000010010 k
b00000000000000000010011001110001 7"
1?"
#400
0?"
#410
b0000000000010011 k
b00000000000000000111001101010100 7"
1?"
#420
0?"
#430
b0000000000010100 k
b00000000000000000011100110101010 7"
1?"
#440
0?"
#450
b0000000000010101 k
b00000000000000000001110011010101 7"
1?"
#460
0?"
#470
b0000000000010110 k
b00000000000000000101011010000000 7"
1?"
#480
0?"
#490
b0000000000010111 k
b00000000000000000010101101000000 7"
1?"
#500
0?"
#510
b0000000000011000 k
b00000000000000000001010110100000 7"
1?"
#520
0?"
#530
b0000000000011001 k
b00000000000000000000101011010000 7"
1?"
#540
0?"
#550
b0000000000011010 k
b00000000000000000000010101101000 7"
1?"
#560
0?"
#570
b0000000000011011 k
b00000000000000000000001010110100 7"
1?"
#580
0?"
#590
b0000000000011100 k
b00000000000000000000000101011010 7"
1?"
#600
0?"
#610
b0000000000011101 k
b00000000000000000000000010101101 7"
1?"
#620
0?"
#630
b0000000000011110 k
b00000000000000000000001000001000 7"
1?"
#640
0?"
#650
b0000000000011111 k
b00000000000000000000000100000100 7"
1?"
#660
0?"
#670
b0000000000100000 k
b00000000000000000000000010000010 7"
1?"
#680
0?"
#690
b0000000000100001 k
b00000000000000000000000001000001 7"
1?"
#700
0?"
#710
b0000000000100010 k
b00000000000000000000000011000100 7"
1?"
#720
0?"
#730
b0000000000100011 k
b00000000000000000000000001100010 7"
1?"
#740
0?"
#750
b0000000000100100 k
b00000000000000000000000000110001 7"
1?"
#760
0?"
#770
b0000000000100101 k
b00000000000000000000000010010100 7"
1?"
#780
0?"
#790
b0000000000100110 k
b00000000000000000000000001001010 7"
1?"
#800
0?"
#810
b0000000000100111 k
b00000000000000000000000000100101 7"
1?"
#820
0?"
#830
b0000000000101000 k
b00000000000000000000000001110000 7"
1?"
#840
0?"
#850
b0000000000101001 k
b00000000000000000000000000111000 7"
1?"
#860
0?"
#870
b0000000000101010 k
b00000000000000000000000000011100 7"
1?"
#880
0?"
#890
b0000000000101011 k
b00000000000000000000000000001110 7"
1?"
#900
0?"
#910
b0000000000101100 k
b00000000000000000000000000000111 7"
1?"
#920
0?"
#930
b0000000000101101 k
b00000000000000000000000000010110 7"
1?"
#940
0?"
#950
b0000000000101110 k
b00000000000000000000000000001011 7"
1?"
#960
0?"
#970
b0000000000101111 k
b00000000000000000000000000100010 7"
1?"
#980
0?"
#990
b0000000000110000 k
b00000000000000000000000000010001 7"
1?"
#1000
0?"
#1010
b0000000000110001 k
b00000000000000000000000000110100 7"
1?"
#1020
0?"
#1030
b0000000000110010 k
b00000000000000000000000000011010 7"
1?"
#1040
0?"
#1050
b0000000000110011 k
b00000000000000000000000000001101 7"
1?"
#1060
0?"
#1070
b0000000000110100 k
b00000000000000000000000000101000 7"
1?"
#1080
0?"
#1090
b0000000000110101 k
b00000000000000000000000000010100 7"
1?"
#1100
0?"
#1110
b0000000000110110 k
b00000000000000000000000000001010 7"
1?"
#1120
0?"
#1130
b0000000000110111 k
b00000000000000000000000000000101 7"
1?"
#1140
0?"
#1150
b0000000000111000 k
b00000000000000000000000000010000 7"
1?"
#1160
0?"
#1170
b0000000000111001 k
b00000000000000000000000000001000 7"
1?"
#1180
0?"
#1190
b0000000000111010 k
b00000000000000000000000000000100 7"
1?"
#1200
0?"
#1210
b0000000000111011 k
b00000000000000000000000000000010 7"
1?"
#1220
0?"
#1230
1;
b0000 C
1S
b0000000000111100 k
b00000000000000000000000000000001 7"
1?"
#1240
0?"
#1250
1+
13
0;
b1111 C
1K
b00000000000000000000001100000000 [
b0001 c
b0000000000111100 s
1?"
#1260
0?"
#1270
03
0K
0S
b0000000000000001 k
b00000000000000000000001100000000 7"
1?"
#1280
0?"
#1290
0+
b0000000000000010 k
b00000000000000000000000110000000 7"
1?"
#1300
0?"
#1310
b0000000000000011 k
b00000000000000000000000011000000 7"
1?"
#1320
0?"
#1330
b0000000000000100 k
b00000000000000000000000001100000 7"
1?"
#1340
0?"
#1350
b0000000000000101 k
b00000000000000000000000000110000 7"
1?"
#1360
0?"
#1370
b0000000000000110 k
b00000000000000000000000000011000 7"
1?"
#1380
0?"
#1390
b0000000000000111 k
b00000000000000000000000000001100 7"
1?"
#1400
0?"
#1410
b0000000000001000 k
b00000000000000000000000000000110 7"
1?"
#1420
0?"
#1430
b0000000000001001 k
b00000000000000000000000000000011 7"
1?"
#1440
0?"
#1450
b0000000000001010 k
b00000000000000000000000000001010 7"
1?"
#1460
0?"
#1470
b0000000000001011 k
b00000000000000000000000000000101 7"
1?"
#1480
0?"
#1490
b0000000000001100 k
b00000000000000000000000000010000 7"
1?"
#1500
0?"
#1510
b0000000000001101 k
b00000000000000000000000000001000 7"
1?"
#1520
0?"
#1530
b0000000000001110 k
b00000000000000000000000000000100 7"
1?"
#1540
0?"
#1550
b0000000000001111 k
b00000000000000000000000000000010 7"
1?"
#1560
0?"
#1570
1;
b0001 C
1S
b0000000000010000 k
b00000000000000000000000000000001 7"
1?"
#1580
0?"
#1590
1+
13
0;
b1111 C
1K
b00000000000000000000001100000001 [
b0010 c
b0000000000010000 t
1?"
#1600
0?"
#1610
03
0K
0S
b0000000000000001 k
b00000000000000000000001100000001 7"
1?"
#1620
0?"
#1630
0+
b0000000000000010 k
b00000000000000000000100100000100 7"
1?"
#1640
0?"
#1650
b0000000000000011 k
b00000000000000000000010010000010 7"
1?"
#1660
0?"
#1670
b0000000000000100 k
b00000000000000000000001001000001 7"
1?"
#1680
0?"
#1690
b0000000000000101 k
b00000000000000000000011011000100 7"
1?"
#1700
0?"
#1710
b0000000000000110 k
b00000000000000000000001101100010 7"
1?"
#1720
0?"
#1730
b0000000000000111 k
b00000000000000000000000110110001 7"
1?"
#1740
0?"
#1750
b0000000000001000 k
b00000000000000000000010100010100 7"
1?"
#1760
0?"
#1770
b0000000000001001 k
b00000000000000000000001010001010 7"
1?"
#1780
0?"
#1790
b0000000000001010 k
b00000000000000000000000101000101 7"
1?"
#1800
0?"
#1810
b0000000000001011 k
b00000000000000000000001111010000 7"
1?"
#1820
0?"
#1830
b0000000000001100 k
b00000000000000000000000111101000 7"
1?"
#1840
0?"
#1850
b0000000000001101 k
b00000000000000000000000011110100 7"
1?"
#1860
0?"
#1870
b0000000000001110 k
b00000000000000000000000001111010 7"
1?"
#1880
0?"
#1890
b0000000000001111 k
b00000000000000000000000000111101 7"
1?"
#1900
0?"
#1910
b0000000000010000 k
b00000000000000000000000010111000 7"
1?"
#1920
0?"
#1930
b0000000000010001 k
b00000000000000000000000001011100 7"
1?"
#1940
0?"
#1950
b0000000000010010 k
b00000000000000000000000000101110 7"
1?"
#1960
0?"
#1970
b0000000000010011 k
b00000000000000000000000000010111 7"
1?"
#1980
0?"
#1990
b0000000000010100 k
b00000000000000000000000001000110 7"
1?"
#2000
0?"
#2010
b0000000000010101 k
b00000000000000000000000000100011 7"
1?"
#2020
0?"
#2030
b0000000000010110 k
b00000000000000000000000001101010 7"
1?"
#2040
0?"
#2050
b0000000000010111 k
b00000000000000000000000000110101 7"
1?"
#2060
0?"
#2070
b0000000000011000 k
b00000000000000000000000010100000 7"
1?"
#2080
0?"
#2090
b0000000000011001 k
b00000000000000000000000001010000 7"
1?"
#2100
0?"
#2110
b0000000000011010 k
b00000000000000000000000000101000 7"
1?"
#2120
0?"
#2130
b0000000000011011 k
b00000000000000000000000000010100 7"
1?"
#2140
0?"
#2150
b0000000000011100 k
b00000000000000000000000000001010 7"
1?"
#2160
0?"
#2170
b0000000000011101 k
b00000000000000000000000000000101 7"
1?"
#2180
0?"
#2190
b0000000000011110 k
b00000000000000000000000000010000 7"
1?"
#2200
0?"
#2210
b0000000000011111 k
b00000000000000000000000000001000 7"
1?"
#2220
0?"
#2230
b0000000000100000 k
b00000000000000000000000000000100 7"
1?"
#2240
0?"
#2250
b0000000000100001 k
b00000000000000000000000000000010 7"
1?"
#2260
0?"
#2270
1;
b0010 C
1S
b0000000000100010 k
b00000000000000000000000000000001 7"
1?"
#2280
0?"
#2290
1+
13
0;
b1111 C
1K
b00000000000000000000001100000010 [
b0011 c
b0000000000100010 u
1?"
#2300
0?"
#2310
03
0K
0S
b0000000000000001 k
b00000000000000000000001100000010 7"
1?"
#2320
0?"
#2330
0+
b0000000000000010 k
b00000000000000000000000110000001 7"
1?"
#2340
0?"
#2350
b0000000000000011 k
b00000000000000000000010010000100 7"
1?"
#2360
0?"
#2370
b0000000000000100 k
b00000000000000000000001001000010 7"
1?"
#2380
0?"
#2390
b0000000000000101 k
b00000000000000000000000100100001 7"
1?"
#2400
0?"
#2410
b0000000000000110 k
b00000000000000000000001101100100 7"
1?"
#2420
0?"
#2430
b0000000000000111 k
b00000000000000000000000110110010 7"
1?"
#2440
0?"
#2450
b0000000000001000 k
b00000000000000000000000011011001 7"
1?"
#2460
0?"
#2470
b0000000000001001 k
b00000000000000000000001010001100 7"
1?"
#2480
0?"
#2490
b0000000000001010 k
b00000000000000000000000101000110 7"
1?"
#2500
0?"
#2510
b0000000000001011 k
b00000000000000000000000010100011 7"
1?"
#2520
0?"
#2530
b0000000000001100 k
b00000000000000000000000111101010 7"
1?"
#2540
0?"
#2550
b0000000000001101 k
b00000000000000000000000011110101 7"
1?"
#2560
0?"
#2570
b0000000000001110 k
b00000000000000000000001011100000 7"
1?"
#2580
0?"
#2590
b0000000000001111 k
b00000000000000000000000101110000 7"
1?"
#2600
0?"
#2610
b0000000000010000 k
b00000000000000000000000010111000 7"
1?"
#2620
0?"
#2630
b0000000000010001 k
b00000000000000000000000001011100 7"
1?"
#2640
0?"
#2650
b0000000000010010 k
b00000000000000000000000000101110 7"
1?"
#2660
0?"
#2670
b0000000000010011 k
b00000000000000000000000000010111 7"
1?"
#2680
0?"
#2690
b0000000000010100 k
b00000000000000000000000001000110 7"
1?"
#2700
0?"
#2710
b0000000000010101 k
b00000000000000000000000000100011 7"
1?"
#2720
0?"
#2730
b0000000000010110 k
b00000000000000000000000001101010 7"
1?"
#2740
0?"
#2750
b0000000000010111 k
b00000000000000000000000000110101 7"
1?"
#2760
0?"
#2770
b0000000000011000 k
b00000000000000000000000010100000 7"
1?"
#2780
0?"
#2790
b0000000000011001 k
b00000000000000000000000001010000 7"
1?"
#2800
0?"
#2810
b0000000000011010 k
b00000000000000000000000000101000 7"
1?"
#2820
0?"
#2830
b0000000000011011 k
b00000000000000000000000000010100 7"
1?"
#2840
0?"
#2850
b0000000000011100 k
b00000000000000000000000000001010 7"
1?"
#2860
0?"
#2870
b0000000000011101 k
b00000000000000000000000000000101 7"
1?"
#2880
0?"
#2890
b0000000000011110 k
b00000000000000000000000000010000 7"
1?"
#2900
0?"
#2910
b0000000000011111 k
b00000000000000000000000000001000 7"
1?"
#2920
0?"
#2930
b0000000000100000 k
b00000000000000000000000000000100 7"
1?"
#2940
0?"
#2950
b0000000000100001 k
b00000000000000000000000000000010 7"
1?"
#2960
0?"
#2970
1;
b0011 C
1S
b0000000000100010 k
b00000000000000000000000000000001 7"
1?"
#2980
0?"
#2990
1+
13
0;
b1111 C
1K
b00000000000000000000001100000011 [
b0100 c
b0000000000100010 v
1?"
#3000
0?"
#3010
03
0K
0S
b0000000000000001 k
b00000000000000000000001100000011 7"
1?"
#3020
0?"
#3030
0+
b0000000000000010 k
b00000000000000000000100100001010 7"
1?"
#3040
0?"
#3050
b0000000000000011 k
b00000000000000000000010010000101 7"
1?"
#3060
0?"
#3070
b0000000000000100 k
b00000000000000000000110110010000 7"
1?"
#3080
0?"
#3090
b0000000000000101 k
b00000000000000000000011011001000 7"
1?"
#3100
0?"
#3110
b0000000000000110 k
b00000000000000000000001101100100 7"
1?"
#3120
0?"
#3130
b0000000000000111 k
b00000000000000000000000110110010 7"
1?"
#3140
0?"
#3150
b0000000000001000 k
b00000000000000000000000011011001 7"
1?"
#3160
0?"
#3170
b0000000000001001 k
b00000000000000000000001010001100 7"
1?"
#3180
0?"
#3190
b0000000000001010 k
b00000000000000000000000101000110 7"
1?"
#3200
0?"
#3210
b0000000000001011 k
b00000000000000000000000010100011 7"
1?"
#3220
0?"
#3230
b0000000000001100 k
b00000000000000000000000111101010 7"
1?"
#3240
0?"
#3250
b0000000000001101 k
b00000000000000000000000011110101 7"
1?"
#3260
0?"
#3270
b0000000000001110 k
b00000000000000000000001011100000 7"
1?"
#3280
0?"
#3290
b0000000000001111 k
b00000000000000000000000101110000 7"
1?"
#3300
0?"
#3310
b0000000000010000 k
b00000000000000000000000010111000 7"
1?"
#3320
0?"
#3330
b0000000000010001 k
b00000000000000000000000001011100 7"
1?"
#3340
0?"
#3350
b0000000000010010 k
b00000000000000000000000000101110 7"
1?"
#3360
0?"
#3370
b0000000000010011 k
b00000000000000000000000000010111 7"
1?"
#3380
0?"
#3390
b0000000000010100 k
b00000000000000000000000001000110 7"
1?"
#3400
0?"
#3410
b0000000000010101 k
b00000000000000000000000000100011 7"
1?"
#3420
0?"
#3430
b0000000000010110 k
b00000000000000000000000001101010 7"
1?"
#3440
0?"
#3450
b0000000000010111 k
b00000000000000000000000000110101 7"
1?"
#3460
0?"
#3470
b0000000000011000 k
b00000000000000000000000010100000 7"
1?"
#3480
0?"
#3490
b0000000000011001 k
b00000000000000000000000001010000 7"
1?"
#3500
0?"
#3510
b0000000000011010 k
b00000000000000000000000000101000 7"
1?"
#3520
0?"
#3530
b0000000000011011 k
b00000000000000000000000000010100 7"
1?"
#3540
0?"
#3550
b0000000000011100 k
b00000000000000000000000000001010 7"
1?"
#3560
0?"
#3570
b0000000000011101 k
b00000000000000000000000000000101 7"
1?"
#3580
0?"
#3590
b0000000000011110 k
b00000000000000000000000000010000 7"
1?"
#3600
0?"
#3610
b0000000000011111 k
b00000000000000000000000000001000 7"
1?"
#3620
0?"
#3630
b0000000000100000 k
b00000000000000000000000000000100 7"
1?"
#3640
0?"
#3650
b0000000000100001 k
b00000000000000000000000000000010 7"
1?"
#3660
0?"
#3670
1;
b0100 C
1S
b0000000000100010 k
b00000000000000000000000000000001 7"
1?"
#3680
0?"
#3690
1+
13
0;
b1111 C
1K
b00000000000000000000001100000100 [
b0101 c
b0000000000100010 w
1?"
#3700
0?"
#3710
03
0K
0S
b0000000000000001 k
b00000000000000000000001100000100 7"
1?"
#3720
0?"
#3730
0+
b0000000000000010 k
b00000000000000000000000110000010 7"
1?"
#3740
0?"
#3750
b0000000000000011 k
b00000000000000000000000011000001 7"
1?"
#3760
0?"
#3770
b0000000000000100 k
b00000000000000000000001001000100 7"
1?"
#3780
0?"
#3790
b0000000000000101 k
b00000000000000000000000100100010 7"
1?"
#3800
0?"
#3810
b0000000000000110 k
b00000000000000000000000010010001 7"
1?"
#3820
0?"
#3830
b0000000000000111 k
b00000000000000000000000110110100 7"
1?"
#3840
0?"
#3850
b0000000000001000 k
b00000000000000000000000011011010 7"
1?"
#3860
0?"
#3870
b0000000000001001 k
b00000000000000000000000001101101 7"
1?"
#3880
0?"
#3890
b0000000000001010 k
b00000000000000000000000101001000 7"
1?"
#3900
0?"
#3910
b0000000000001011 k
b00000000000000000000000010100100 7"
1?"
#3920
0?"
#3930
b0000000000001100 k
b00000000000000000000000001010010 7"
1?"
#3940
0?"
#3950
b0000000000001101 k
b00000000000000000000000000101001 7"
1?"
#3960
0?"
#3970
b0000000000001110 k
b00000000000000000000000001111100 7"
1?"
#3980
0?"
#3990
b0000000000001111 k
b00000000000000000000000000111110 7"
1?"
#4000
0?"
#4010
b0000000000010000 k
b00000000000000000000000000011111 7"
1?"
#4020
0?"
#4030
b0000000000010001 k
b00000000000000000000000001011110 7"
1?"
#4040
0?"
#4050
b0000000000010010 k
b00000000000000000000000000101111 7"
1?"
#4060
0?"
#4070
b0000000000010011 k
b00000000000000000000000010001110 7"
1?"
#4080
0?"
#4090
b0000000000010100 k
b00000000000000000000000001000111 7"
1?"
#4100
0?"
#4110
b0000000000010101 k
b00000000000000000000000011010110 7"
1?"
#4120
0?"
#4130
b0000000000010110 k
b00000000000000000000000001101011 7"
1?"
#4140
0?"
#4150
b0000000000010111 k
b00000000000000000000000101000010 7"
1?"
#4160
0?"
#4170
b0000000000011000 k
b00000000000000000000000010100001 7"
1?"
#4180
0?"
#4190
b0000000000011001 k
b00000000000000000000000111100100 7"
1?"
#4200
0?"
#4210
b0000000000011010 k
b00000000000000000000000011110010 7"
1?"
#4220
0?"
#4230
b0000000000011011 k
b00000000000000000000000001111001 7"
1?"
#4240
0?"
#4250
b0000000000011100 k
b00000000000000000000000101101100 7"
1?"
#4260
0?"
#4270
b0000000000011101 k
b00000000000000000000000010110110 7"
1?"
#4280
0?"
#4290
b0000000000011110 k
b00000000000000000000000001011011 7"
1?"
#4300
0?"
#4310
b0000000000011111 k
b00000000000000000000000100010010 7"
1?"
#4320
0?"
#4330
b0000000000100000 k
b00000000000000000000000010001001 7"
1?"
#4340
0?"
#4350
b0000000000100001 k
b00000000000000000000000110011100 7"
1?"
#4360
0?"
#4370
b0000000000100010 k
b00000000000000000000000011001110 7"
1?"
#4380
0?"
#4390
b0000000000100011 k
b00000000000000000000000001100111 7"
1?"
#4400
0?"
#4410
b0000000000100100 k
b00000000000000000000000100110110 7"
1?"
#4420
0?"
#4430
b0000000000100101 k
b00000000000000000000000010011011 7"
1?"
#4440
0?"
#4450
b0000000000100110 k
b00000000000000000000000111010010 7"
1?"
#4460
0?"
#4470
b0000000000100111 k
b00000000000000000000000011101001 7"
1?"
#4480
0?"
#4490
b0000000000101000 k
b00000000000000000000001010111100 7"
1?"
#4500
0?"
#4510
b0000000000101001 k
b00000000000000000000000101011110 7"
1?"
#4520
0?"
#4530
b0000000000101010 k
b00000000000000000000000010101111 7"
1?"
#4540
0?"
#4550
b0000000000101011 k
b00000000000000000000001000001110 7"
1?"
#4560
0?"
#4570
b0000000000101100 k
b00000000000000000000000100000111 7"
1?"
#4580
0?"
#4590
b0000000000101101 k
b00000000000000000000001100010110 7"
1?"
#4600
0?"
#4610
b0000000000101110 k
b00000000000000000000000110001011 7"
1?"
#4620
0?"
#4630
b0000000000101111 k
b00000000000000000000010010100010 7"
1?"
#4640
0?"
#4650
b0000000000110000 k
b00000000000000000000001001010001 7"
1?"
#4660
0?"
#4670
b0000000000110001 k
b00000000000000000000011011110100 7"
1?"
#4680
0?"
#4690
b0000000000110010 k
b00000000000000000000001101111010 7"
1?"
#4700
0?"
#4710
b0000000000110011 k
b00000000000000000000000110111101 7"
1?"
#4720
0?"
#4730
b0000000000110100 k
b00000000000000000000010100111000 7"
1?"
#4740
0?"
#4750
b0000000000110101 k
b00000000000000000000001010011100 7"
1?"
#4760
0?"
#4770
b0000000000110110 k
b00000000000000000000000101001110 7"
1?"
#4780
0?"
#4790
b0000000000110111 k
b00000000000000000000000010100111 7"
1?"
#4800
0?"
#4810
b0000000000111000 k
b00000000000000000000000111110110 7"
1?"
#4820
0?"
#4830
b0000000000111001 k
b00000000000000000000000011111011 7"
1?"
#4840
0?"
#4850
b0000000000111010 k
b00000000000000000000001011110010 7"
1?"
#4860
0?"
#4870
b0000000000111011 k
b00000000000000000000000101111001 7"
1?"
#4880
0?"
#4890
b0000000000111100 k
b00000000000000000000010001101100 7"
1?"
#4900
0?"
#4910
b0000000000111101 k
b00000000000000000000001000110110 7"
1?"
#4920
0?"
#4930
b0000000000111110 k
b00000000000000000000000100011011 7"
1?"
#4940
0?"
#4950
b0000000000111111 k
b00000000000000000000001101010010 7"
1?"
#4960
0?"
#4970
b0000000001000000 k
b00000000000000000000000110101001 7"
1?"
#4980
0?"
#4990
b0000000001000001 k
b00000000000000000000010011111100 7"
1?"
#5000
0?"
#5010
b0000000001000010 k
b00000000000000000000001001111110 7"
1?"
#5020
0?"
#5030
b0000000001000011 k
b00000000000000000000000100111111 7"
1?"
#5040
0?"
#5050
b0000000001000100 k
b00000000000000000000001110111110 7"
1?"
#5060
0?"
#5070
b0000000001000101 k
b00000000000000000000000111011111 7"
1?"
#5080
0?"
#5090
b0000000001000110 k
b00000000000000000000010110011110 7"
1?"
#5100
0?"
#5110
b0000000001000111 k
b00000000000000000000001011001111 7"
1?"
#5120
0?"
#5130
b0000000001001000 k
b00000000000000000000100001101110 7"
1?"
#5140
0?"
#5150
b0000000001001001 k
b00000000000000000000010000110111 7"
1?"
#5160
0?"
#5170
b0000000001001010 k
b00000000000000000000110010100110 7"
1?"
#5180
0?"
#5190
b0000000001001011 k
b00000000000000000000011001010011 7"
1?"
#5200
0?"
#5210
b0000000001001100 k
b00000000000000000001001011111010 7"
1?"
#5220
0?"
#5230
b0000000001001101 k
b00000000000000000000100101111101 7"
1?"
#5240
0?"
#5250
b0000000001001110 k
b00000000000000000001110001111000 7"
1?"
#5260
0?"
#5270
b0000000001001111 k
b00000000000000000000111000111100 7"
1?"
#5280
0?"
#5290
b0000000001010000 k
b00000000000000000000011100011110 7"
1?"
#5300
0?"
#5310
b0000000001010001 k
b00000000000000000000001110001111 7"
1?"
#5320
0?"
#5330
b0000000001010010 k
b00000000000000000000101010101110 7"
1?"
#5340
0?"
#5350
b0000000001010011 k
b00000000000000000000010101010111 7"
1?"
#5360
0?"
#5370
b0000000001010100 k
b00000000000000000001000000000110 7"
1?"
#5380
0?"
#5390
b0000000001010101 k
b00000000000000000000100000000011 7"
1?"
#5400
0?"
#5410
b0000000001010110 k
b00000000000000000001100000001010 7"
1?"
#5420
0?"
#5430
b0000000001010111 k
b00000000000000000000110000000101 7"
1?"
#5440
0?"
#5450
b0000000001011000 k
b00000000000000000010010000010000 7"
1?"
#5460
0?"
#5470
b0000000001011001 k
b00000000000000000001001000001000 7"
1?"
#5480
0?"
#5490
b0000000001011010 k
b00000000000000000000100100000100 7"
1?"
#5500
0?"
#5510
b0000000001011011 k
b00000000000000000000010010000010 7"
1?"
#5520
0?"
#5530
b0000000001011100 k
b00000000000000000000001001000001 7"
1?"
#5540
0?"
#5550
b0000000001011101 k
b00000000000000000000011011000100 7"
1?"
#5560
0?"
#5570
b0000000001011110 k
b00000000000000000000001101100010 7"
1?"
#5580
0?"
#5590
b0000000001011111 k
b00000000000000000000000110110001 7"
1?"
#5600
0?"
#5610
b0000000001100000 k
b00000000000000000000010100010100 7"
1?"
#5620
0?"
#5630
b0000000001100001 k
b00000000000000000000001010001010 7"
1?"
#5640
0?"
#5650
b0000000001100010 k
b00000000000000000000000101000101 7"
1?"
#5660
0?"
#5670
b0000000001100011 k
b00000000000000000000001111010000 7"
1?"
#5680
0?"
#5690
b0000000001100100 k
b00000000000000000000000111101000 7"
1?"
#5700
0?"
#5710
b0000000001100101 k
b00000000000000000000000011110100 7"
1?"
#5720
0?"
#5730
b0000000001100110 k
b00000000000000000000000001111010 7"
1?"
#5740
0?"
#5750
b0000000001100111 k
b00000000000000000000000000111101 7"
1?"
#5760
0?"
#5770
b0000000001101000 k
b00000000000000000000000010111000 7"
1?"
#5780
0?"
#5790
b0000000001101001 k
b00000000000000000000000001011100 7"
1?"
#5800
0?"
#5810
b0000000001101010 k
b00000000000000000000000000101110 7"
1?"
#5820
0?"
#5830
b0000000001101011 k
b00000000000000000000000000010111 7"
1?"
#5840
0?"
#5850
b0000000001101100 k
b00000000000000000000000001000110 7"
1?"
#5860
0?"
#5870
b0000000001101101 k
b00000000000000000000000000100011 7"
1?"
